core/__init__.py
core/execution/__init__.py
core/execution/actor_manager.py
core/execution/reduce_result_dict_fn.py
core/execution/scaling_config.py
core/execution/session.py
core/execution/worker.py
core/execution/worker_group.py
core/execution/worker_group_config.py
core/tests/__init__.py
core/tests/test_actor_namager.py
core/tests/test_worker.py
core/tests/test_worker_group.py
fedlib-0.0.12345.dist-info/LICENSE
fedlib-0.0.12345.dist-info/METADATA
fedlib-0.0.12345.dist-info/WHEEL
fedlib-0.0.12345.dist-info/entry_points.txt
fedlib-0.0.12345.dist-info/RECORD
