Metadata-Version: 2.1
Name: fedlib
Version: 0.0.12345
Summary: A Scalable Federated Learning Library
Home-page: https://fllib.github.io
License: Apache-2.0
Keywords: deep-learning,pytorch,federated-learning
Author: Shenghui Li
Author-email: shenghui.li@it.uu.se
Requires-Python: >=3.9,<4.0
Classifier: Development Status :: 5 - Production/Stable
Classifier: License :: OSI Approved :: Apache Software License
Classifier: Programming Language :: Python
Classifier: Programming Language :: Python :: 3
Classifier: Programming Language :: Python :: 3.9
Classifier: Programming Language :: Python :: 3.10
Classifier: Programming Language :: Python :: 3.11
Classifier: Programming Language :: Python :: 3.12
Classifier: Programming Language :: Python :: 3 :: Only
Classifier: Programming Language :: Python :: 3.8
Requires-Dist: dm_tree
Requires-Dist: matplotlib (>=3.8.1,<4.0.0)
Requires-Dist: numpy (>=1.26.1,<2.0.0)
Requires-Dist: pre-commit
Requires-Dist: pytest
Requires-Dist: ray (>=2.8.0,<3.0.0)
Requires-Dist: requests (>=2.27.1,<3.0.0)
Requires-Dist: scikit-learn (>=1.3.2,<2.0.0)
Requires-Dist: setuptools
Requires-Dist: torch (>=2.0.1,<3.0.0)
Requires-Dist: torchaudio
Requires-Dist: torchmetrics
Requires-Dist: torchvision (>=0.15.2,<0.16.0)
Requires-Dist: tqdm
Requires-Dist: typer
Requires-Dist: wandb (>=0.15.12,<0.16.0)
Project-URL: Documentation, https://fllib.readthedocs.io
Project-URL: Repository, https://github.com/fllib/fllib
